<package>
  <description brief="image_server_prototype">

     image_server_prototype

  </description>
  <author>Edward T. Kaszubski, Rand Voorhies</author>
  <license>BSD</license>
  <review status="unreviewed" notes=""/>
  <url>http://ros.org/wiki/image_server</url>
  <depend package="base_libs_prototype"/>
  <depend package="nodelet"/>
  
  <export>
    <nodelet plugin="${prefix}/nodelet_plugins.xml" />
    <cpp cflags="-I${prefix}/include" lflags="-Wl,-rpath,${prefix}/lib -L${prefix}/lib"/>
  </export>
</package>


