<library path="lib/libimage_transforms_nodelets">

  <class name="image_transforms/image_scaler" type="image_transforms::ImageScalerNodelet" base_class_type="nodelet::Nodelet">
    <description>
      todo: fill this in
    </description>
  </class>

  <class name="image_transforms/image_rotater" type="image_transforms::ImageRotaterNodelet" base_class_type="nodelet::Nodelet">
    <description>
      todo: fill this in
    </description>
  </class>

  <class name="image_transforms/color_transform" type="image_transforms::ColorTransformNodelet" base_class_type="nodelet::Nodelet">
    <description>
      todo: fill this in
    </description>
  </class>
</library>
